luna_code/__init__.py
luna_code/__main__.py
luna_code/main.lce
luna_code/main.py
luna_code-0.1.2.dist-info/entry_points.txt
luna_code-0.1.2.dist-info/METADATA
luna_code-0.1.2.dist-info/WHEEL
luna_code-0.1.2.dist-info/RECORD
