Metadata-Version: 2.3
Name: luna_code
Version: 0.1.2
Summary: A litterally useless coding language built in python.
Author: FelDev
Author-email: lparsons@saffron.net
Requires-Python: >=3.12
Classifier: Programming Language :: Python :: 3
Classifier: Programming Language :: Python :: 3.12
Classifier: Programming Language :: Python :: 3.13
Requires-Dist: typer (>=0.15.1,<0.16.0)
